odoo8_addon_product_weight-8.0.0.2.0-py2.7-nspkg.pth
odoo8_addon_product_weight-8.0.0.2.0.dist-info/top_level.txt
odoo8_addon_product_weight-8.0.0.2.0.dist-info/WHEEL
odoo8_addon_product_weight-8.0.0.2.0.dist-info/RECORD
odoo8_addon_product_weight-8.0.0.2.0.dist-info/metadata.json
odoo8_addon_product_weight-8.0.0.2.0.dist-info/DESCRIPTION.rst
odoo8_addon_product_weight-8.0.0.2.0.dist-info/METADATA
odoo8_addon_product_weight-8.0.0.2.0.dist-info/namespace_packages.txt
odoo_addons/product_weight/__openerp__.py
odoo_addons/product_weight/__init__.py
odoo_addons/product_weight/product_view.xml
odoo_addons/product_weight/bom.py
odoo_addons/product_weight/README.rst
odoo_addons/product_weight/i18n/product_weight.pot
odoo_addons/product_weight/i18n/fr.po
odoo_addons/product_weight/wizard/product_weight_update_view.xml
odoo_addons/product_weight/wizard/__init__.py
odoo_addons/product_weight/wizard/product_weight_update.py
odoo_addons/product_weight/tests/__init__.py
odoo_addons/product_weight/tests/test_compute_bom_weight.py
odoo_addons/product_weight/static/description/icon.png
